cluster/__init__.py
cluster/cluster.py
cluster/linkage.py
cluster/matrix.py
cluster/util.py
cluster/version.txt
cluster/method/__init__.py
cluster/method/base.py
cluster/method/hierarchical.py
cluster/method/kmeans.py
cluster-1.4.1.dist-info/DESCRIPTION.rst
cluster-1.4.1.dist-info/METADATA
cluster-1.4.1.dist-info/RECORD
cluster-1.4.1.dist-info/WHEEL
cluster-1.4.1.dist-info/metadata.json
cluster-1.4.1.dist-info/top_level.txt
